chinus_emotions/__init__.py
chinus_emotions/data/__init__.py
chinus_emotions/data/db/__init__.py
chinus_emotions/data/db/emotions.db
chinus_emotions/src/db/__init__.py
chinus_emotions/src/db/db_connect.py
chinus_emotions/src/emotions/__init__.py
chinus_emotions/src/emotions/emotions.py
chinus_emotions/src/main/__init__.py
chinus_emotions/src/main/main.py
chinus_emotions-3.1.6.dist-info/METADATA
chinus_emotions-3.1.6.dist-info/WHEEL
chinus_emotions-3.1.6.dist-info/top_level.txt
chinus_emotions-3.1.6.dist-info/RECORD
