Metadata-Version: 2.1
Name: chinus_emotions
Version: 3.1.6
Summary: This is a chinus Python package.
Author-email: Chinu9653 <juyoung9653@gmail.com>
License: MIT
Project-URL: Homepage, https://github.com/juyoung9653/emotions
Classifier: Programming Language :: Python :: 3
Classifier: License :: OSI Approved :: MIT License
Requires-Python: >=3.6
